manifesto/__init__.py
manifesto/manifest.py
manifesto/urls.py
manifesto/views.py
manifesto/templates/manifesto/manifest.appcache
manifesto-0.5.dist-info/DESCRIPTION.rst
manifesto-0.5.dist-info/METADATA
manifesto-0.5.dist-info/pydist.json
manifesto-0.5.dist-info/RECORD
manifesto-0.5.dist-info/top_level.txt
manifesto-0.5.dist-info/WHEEL
tests/__init__.py
tests/manifest.py
tests/models.py
tests/settings.py
tests/urls.py
tests/tests/__init__.py
tests/tests/test_views.py
